rasa_model_report/__init__.py
rasa_model_report/main.py
rasa_model_report/controllers/__init__.py
rasa_model_report/controllers/controller.py
rasa_model_report/controllers/csv_controller.py
rasa_model_report/controllers/e2e_coverage_controller.py
rasa_model_report/controllers/json_controller.py
rasa_model_report/controllers/markdown_controller.py
rasa_model_report/controllers/model_report.py
rasa_model_report/controllers/nlu_controller.py
rasa_model_report/helpers/__init__.py
rasa_model_report/helpers/constants.py
rasa_model_report/helpers/type_aliases.py
rasa_model_report/helpers/utils.py
rasa_model_report-1.5.0.dist-info/LICENSE
rasa_model_report-1.5.0.dist-info/METADATA
rasa_model_report-1.5.0.dist-info/WHEEL
rasa_model_report-1.5.0.dist-info/entry_points.txt
rasa_model_report-1.5.0.dist-info/top_level.txt
rasa_model_report-1.5.0.dist-info/RECORD
