Metadata-Version: 2.1
Name: rasa-model-report
Version: 1.5.0
Summary: Simple open-source Rasa command-line add-on that generates training model health reports for your projects.
Home-page: https://github.com/brunohjs/rasa-model-report
Author: Bruno Justo
Author-email: brunohjs@gmail.com
License: Apache 2.0
Requires-Python: >=3.8
License-File: LICENSE
Requires-Dist: Click
Requires-Dist: requests ==2.28.1
Requires-Dist: pyyaml >=6.0
